LICENSE
README.md
setup.py
PyAPD/__init__.py
PyAPD/apds.py
PyAPD/ebsd_utils.py
PyAPD/geometry_utils.py
PyAPD/log_res.py
PyAPD/log_res_utils.py
PyAPD/override_optimality_condition.py
PyAPD.egg-info/PKG-INFO
PyAPD.egg-info/SOURCES.txt
PyAPD.egg-info/dependency_links.txt
PyAPD.egg-info/requires.txt
PyAPD.egg-info/top_level.txt