Metadata-Version: 2.2
Name: PyAPD
Version: 0.1.4
Summary: A Python library for generating (optimal) anisotropic power diagrams
Home-page: https://github.com/mbuze/PyAPD
Author: Maciej Buze, Steve Roper, David Bourne
Author-email: maciej.buze@gmail.com
Classifier: Programming Language :: Python :: 3
Classifier: License :: OSI Approved :: MIT License
Classifier: Operating System :: OS Independent
Requires-Python: >=3.6
License-File: LICENSE
Requires-Dist: numpy
Requires-Dist: pykeops
Requires-Dist: torch
Requires-Dist: pytorch-minimize
Requires-Dist: matplotlib
Requires-Dist: scipy
Dynamic: author
Dynamic: author-email
Dynamic: classifier
Dynamic: description
Dynamic: description-content-type
Dynamic: home-page
Dynamic: requires-dist
Dynamic: requires-python
Dynamic: summary
